pypi_test_capture/__init__.py
pypi_test_capture/cli.py
pypi_test_capture-0.0.1.dist-info/METADATA
pypi_test_capture-0.0.1.dist-info/WHEEL
pypi_test_capture-0.0.1.dist-info/entry_points.txt
pypi_test_capture-0.0.1.dist-info/RECORD
